[
  {
    "number": 11,
    "state": "DONE",
    "title": "Dockerize backend and database"
  },
  {
    "number": 9,
    "state": "IN_PROGRESS",
    "title": "Phase 4: UI Polish & Animations"
  },
  {
    "number": 8,
    "state": "DONE",
    "title": "Phase 4: Integrate Discord Embedded App SDK"
  },
  {
    "number": 7,
    "state": "DONE",
    "title": "Phase 4: Build Discord Client Interface"
  },
  {
    "number": 6,
    "state": "DONE",
    "title": "Phase 3: Implement Match-making Capabilities"
  },
  {
    "number": 5,
    "state": "DONE",
    "title": "Phase 3: Setup Colyseus Node.js Server & Room State"
  },
  {
    "number": 4,
    "state": "DONE",
    "title": "Phase 2: Write Unit Tests for Core Game Logic"
  },
  {
    "number": 3,
    "state": "DONE",
    "title": "Phase 2: Implement Core Durak Game Logic & Rules"
  },
  {
    "number": 2,
    "state": "TODO",
    "title": "Phase 1: Implement GitHub Actions CI Pipeline"
  },
  {
    "number": 1,
    "state": "DONE",
    "title": "Phase 1: Repository Scaffold & Base Tooling"
  }
]